Workbook

Sheet Assumptions
A1: Assumption | B1: Value | C1: Unit
A2: Monthly volume growth | B2: 0.03 | C2: %
A3: Unit price | B3: 12.5 | C3: $
A4: Unit cost | B4: 7 | C4: $
A5: Starting volume | B5: 1000 | C5: units

Sheet Monthly
A1: Monthly forecast
A3: Month | B3: unit | C3: 45658 | D3: 45689 | E3: 45717 | F3: 45748 | G3: 45778 | H3: 45809 | I3: 45839 | J3: 45870 | K3: 45901 | L3: 45931 | M3: 45962 | N3: 45992
A5: Volume | B5: units | C5: =Assumptions!$B$5 -> 1000 | D5: =C5*(1+Assumptions!$B$2) -> 1030 | E5: =D5*(1+Assumptions!$B$2) -> 1060.9 | F5: =E5*(1+Assumptions!$B$2) -> 1092.727 | G5: =F5*(1+Assumptions!$B$2) -> 1125.5088 | H5: =G5*(1+Assumptions!$B$2) -> 1159.2741 | I5: =H5*(1+Assumptions!$B$2) -> 1194.0523 | J5: =I5*(1+Assumptions!$B$2) -> 1229.8739 | K5: =J5*(1+Assumptions!$B$2) -> 1266.7701 | ... N5: =M5*(1+Assumptions!$B$2) -> 1384.2339
A6: Revenue | B6: $ | C6: =C5*Assumptions!$B$3 -> 12500 | D6: =D5*Assumptions!$B$3 -> 12875 | E6: =E5*Assumptions!$B$3 -> 13261.25 | F6: =F5*Assumptions!$B$3 -> 13659.088 | G6: =G5*Assumptions!$B$3 -> 14068.86 | H6: =H5*Assumptions!$B$3 -> 14490.926 | I6: =I5*Assumptions!$B$3 -> 14925.654 | J6: =J5*Assumptions!$B$3 -> 15373.423 | ... N6: =N5*Assumptions!$B$3 -> 17302.923
A7: Cost | B7: $ | C7: =-C5*Assumptions!$B$4 -> -7000 | D7: =-D5*Assumptions!$B$4 -> -7210 | E7: =-E5*Assumptions!$B$4 -> -7426.3 | F7: =-F5*Assumptions!$B$4 -> -7649.089 | G7: =-G5*Assumptions!$B$4 -> -7878.5617 | H7: =-H5*Assumptions!$B$4 -> -8114.9185 | I7: =-I5*Assumptions!$B$4 -> -8358.3661 | J7: =-J5*Assumptions!$B$4 -> -8609.1171 | ... N7: =-N5*Assumptions!$B$4 -> -9689.6371
A8: Gross profit | B8: $ | C8: =C6+C7 -> 5500 | D8: =D6+D7 -> 5665 | E8: =E6+E7 -> 5834.95 | F8: =F6+F7 -> 6009.9985 | G8: =G6+G7 -> 6190.2985 | H8: =H6+H7 -> 6376.0074 | I8: =I6+I7 -> 6567.2876 | J8: =J6+J7 -> 6764.3063 | ... N8: =N6+N7 -> 7613.2863

Sheet Summary
A1: Metric | B1: Value
A2: Total revenue | B2: =SUM(Monthly!C6:N6) -> 177400.37
A3: Total gross profit | B3: =SUM(Monthly!C8:N8) -> 78056.163
A4: Gross margin | B4: =B3/B2 -> 0.44

Sheet Sales data
A1: Date | B1: Region | C1: Amount
A2: 45658 | B2: North | C2: 100
A3: 45690 | B3: South | C3: 107
A4: 45719 | B4: East | C4: 114
A5: 45751 | B5: North | C5: 121
A6: 45782 | B6: South | C6: 128
A7: 45814 | B7: East | C7: 135
A8: 45845 | B8: North | C8: 142
A9: 45877 | B9: South | C9: 149
A10: 45909 | B10: East | C10: 156
A11: 45940 | B11: North | C11: 163
A12: 45972 | B12: South | C12: 170
A13: 46003 | B13: East | C13: 177
... A51: 45710 | B51: South | C51: 443
